bot/__init__.py
bot/config.py
bot/sites.py
bot/scripts/__init__.py
bot/scripts/bot.py
apache_bot-0.2.1.dist-info/METADATA
apache_bot-0.2.1.dist-info/WHEEL
apache_bot-0.2.1.dist-info/entry_points.txt
apache_bot-0.2.1.dist-info/top_level.txt
apache_bot-0.2.1.dist-info/RECORD
