Metadata-Version: 2.1
Name: apache-bot
Version: 0.2.1
Summary: A brief description of your project
Home-page: https://github.com/yourusername/your_project
Author: Ivan
Author-email: your.email@example.com
License: UNKNOWN
Platform: UNKNOWN
Classifier: Programming Language :: Python :: 3
Classifier: License :: OSI Approved :: MIT License
Classifier: Operating System :: OS Independent
Requires-Python: >=3.6
Requires-Dist: paramiko
Requires-Dist: python-telegram-bot
